Metadata-Version: 1.0
Name: hc-probability
Version: 1.0
Summary: Gaussian and Binomial distributions
Home-page: UNKNOWN
Author: Uyioghosa Nosa-Ihaza
Author-email: ihazauyi@gmail.com
License: UNKNOWN
Platform: UNKNOWN
